source/__init__.py
source/cli.py
source/scrapper.py
acl_iitbbs-0.5.dist-info/LICENSE
acl_iitbbs-0.5.dist-info/METADATA
acl_iitbbs-0.5.dist-info/WHEEL
acl_iitbbs-0.5.dist-info/entry_points.txt
acl_iitbbs-0.5.dist-info/top_level.txt
acl_iitbbs-0.5.dist-info/RECORD
